MANIFEST.in
README.md
setup.py
PointMatcher/__init__.py
PointMatcher/__main__.py
PointMatcher/mainwindow.py
PointMatcher/settings.py
PointMatcher.egg-info/PKG-INFO
PointMatcher.egg-info/SOURCES.txt
PointMatcher.egg-info/dependency_links.txt
PointMatcher.egg-info/entry_points.txt
PointMatcher.egg-info/requires.txt
PointMatcher.egg-info/top_level.txt
PointMatcher/actions/__init__.py
PointMatcher/actions/autosaving.py
PointMatcher/actions/close.py
PointMatcher/actions/editkeypointmode.py
PointMatcher/actions/editmatchmode.py
PointMatcher/actions/export.py
PointMatcher/actions/newproject.py
PointMatcher/actions/openannotdir.py
PointMatcher/actions/openimagedir.py
PointMatcher/actions/opennextview.py
PointMatcher/actions/openprevview.py
PointMatcher/actions/quitapp.py
PointMatcher/actions/save.py
PointMatcher/actions/showinfo.py
PointMatcher/data/__init__.py
PointMatcher/data/matching.py
PointMatcher/data/op.py
PointMatcher/data/painter.py
PointMatcher/widgets/__init__.py
PointMatcher/widgets/canvas.py
PointMatcher/widgets/scrollwidget.py
PointMatcher/widgets/toolbar.py
PointMatcher/widgets/viewiwidget.py
PointMatcher/widgets/viewjwidget.py
PointMatcher/widgets/zoomwidget.py